flexstack/__init__.py
flexstack/applications/__init__.py
flexstack/applications/road_hazard_signalling_service/__init__.py
flexstack/applications/road_hazard_signalling_service/emergency_vehicle_approaching_service.py
flexstack/applications/road_hazard_signalling_service/service_access_point.py
flexstack/btp/__init__.py
flexstack/btp/btp_header.py
flexstack/btp/router.py
flexstack/btp/service_access_point.py
flexstack/facilities/__init__.py
flexstack/facilities/ca_basic_service/__init__.py
flexstack/facilities/ca_basic_service/ca_basic_service.py
flexstack/facilities/ca_basic_service/cam_asn1.py
flexstack/facilities/ca_basic_service/cam_coder.py
flexstack/facilities/ca_basic_service/cam_ldm_adaptation.py
flexstack/facilities/ca_basic_service/cam_reception_management.py
flexstack/facilities/ca_basic_service/cam_transmission_management.py
flexstack/facilities/decentralized_environmental_notification_service/__init__.py
flexstack/facilities/decentralized_environmental_notification_service/den_service.py
flexstack/facilities/decentralized_environmental_notification_service/denm_coder.py
flexstack/facilities/decentralized_environmental_notification_service/denm_reception_management.py
flexstack/facilities/decentralized_environmental_notification_service/denm_transmission_management.py
flexstack/facilities/decentralized_environmental_notification_service/asn1/__init__.py
flexstack/facilities/decentralized_environmental_notification_service/asn1/denm_asn1.py
flexstack/facilities/local_dynamic_map/__init__.py
flexstack/facilities/local_dynamic_map/database.py
flexstack/facilities/local_dynamic_map/dictionary_database.py
flexstack/facilities/local_dynamic_map/exceptions.py
flexstack/facilities/local_dynamic_map/factory.py
flexstack/facilities/local_dynamic_map/if_ldm_1.py
flexstack/facilities/local_dynamic_map/if_ldm_2.py
flexstack/facilities/local_dynamic_map/if_ldm_3.py
flexstack/facilities/local_dynamic_map/if_ldm_4.py
v2xflexstack-0.10.9.dist-info/LICENSE
v2xflexstack-0.10.9.dist-info/METADATA
v2xflexstack-0.10.9.dist-info/WHEEL
v2xflexstack-0.10.9.dist-info/top_level.txt
v2xflexstack-0.10.9.dist-info/RECORD
